setup.py
callrate/__init__.py
callrate/callrate.py
callrate.egg-info/PKG-INFO
callrate.egg-info/SOURCES.txt
callrate.egg-info/dependency_links.txt
callrate.egg-info/top_level.txt