Metadata-Version: 1.0
Name: callrate
Version: 2018.4
Summary: Package to manage functions call rate
Home-page: https://gitlab.com/goblenus/requestslimitrate
Author: Anton Bautkin
Author-email: antonbautkin@gmail.com
License: MIT
Platform: UNKNOWN
